LICENSE
MANIFEST.in
Makefile
README.rst
VERSION
setup.py
test_requirements.txt
jujuresources/__init__.py
jujuresources/backend.py
jujuresources/cli.py
jujuresources/version.py
jujuresources.egg-info/PKG-INFO
jujuresources.egg-info/SOURCES.txt
jujuresources.egg-info/dependency_links.txt
jujuresources.egg-info/entry_points.txt
jujuresources.egg-info/pbr.json
jujuresources.egg-info/requires.txt
jujuresources.egg-info/top_level.txt