Metadata-Version: 1.0
Name: jujuresources
Version: 0.2.11
Summary: Helpers for Juju Charms to load external resources
Home-page: https://github.com/juju-solutions/jujuresources
Author: Cory Johns
Author-email: cory.johns@canonical.com
License: MIT License
Platform: UNKNOWN
